a2y_atsui.cp312-win_amd64.pyd
a2y_atsui-1.0.0.dist-info/LICENSE
a2y_atsui-1.0.0.dist-info/METADATA
a2y_atsui-1.0.0.dist-info/WHEEL
a2y_atsui-1.0.0.dist-info/top_level.txt
a2y_atsui-1.0.0.dist-info/RECORD
